<?xml version="1.0" encoding="UTF-8" standalone="yes"?>



<item>
<title>[COLOR blue]Camaron en el bautizo de su hijo 1988 parte 1/2[/COLOR]</title>
<link>plugin://plugin.video.youtube/?action=play_video&amp;videoid=AuiuTpxJbko</link>
<thumbnail>https://i.ytimg.com/vi/AuiuTpxJbko/hqdefault.jpg</thumbnail>
</item>

<item>
<title>[COLOR blue]Camaron en el bautizo de su hijo 1988 parte 2/2[/COLOR]</title>
<link>plugin://plugin.video.youtube/?action=play_video&amp;videoid=55KoR5DY2G8</link>
<thumbnail>https://i.ytimg.com/vi/AuiuTpxJbko/hqdefault.jpg</thumbnail>
</item>


<item>
<title>[COLOR green]ESPECIAL 25 AÑOS[/COLOR][COLOR yellow] LA GARGANTA DE DIOS[/COLOR]</title>
<link>plugin://plugin.video.youtube/?action=play_video&amp;videoid=YXfv97n0B-0</link>
<thumbnail>https://i.ytimg.com/vi/YXfv97n0B-0/maxresdefault.jpg</thumbnail>
</item>

<item>
<title>[COLOR green] Especial 20 años   [/COLOR][COLOR yellow] sin Camarón[/COLOR]</title>
<link>plugin://plugin.video.youtube/?action=play_video&amp;videoid=</link>
<thumbnail>http://www.culturaencadena.com/images/stories/contenido_2012/20aosincamaron.jpg</thumbnail>
</item>


<item>
<title>[COLOR green] El Legado [/COLOR][COLOR yellow] Camarón de la Isla[/COLOR]</title>
<link>plugin://plugin.video.youtube/?action=play_video&amp;videoid=R56tvOz6UOI</link>
<thumbnail>http://www.cuadernodearte.es/foto-video-cine/camaron-04.jpg</thumbnail>
</item>

<item>
<title>[COLOR green]Perfil. 20 años de la muerte [/COLOR][COLOR yellow] de Camarón [/COLOR]</title>
<link>plugin://plugin.video.youtube/?action=play_video&amp;videoid=uDmE4u39ERU</link>
<thumbnail>https://i.ytimg.com/vi/uDmE4u39ERU/hqdefault.jpg</thumbnail>
</item>


<item>
<title>[COLOR green] Documental. Camarón[/COLOR][COLOR yellow] El día que empezó la leyenda. 2012 [/COLOR]</title>
<link>plugin://plugin.video.youtube/?action=play_video&amp;videoid=vE8gcySt6nM</link>
<thumbnail>https://ytimg.googleusercontent.com/vi/7xvEhUTrW_E/mqdefault.jpg</thumbnail>
</item>


<item>
<title>[COLOR green]CAMARÓN DE LA ISLA     [/COLOR][COLOR yellow]X ANIVERSARIO [/COLOR]</title>
<link>plugin://plugin.video.youtube/?action=play_video&amp;videoid=bmsJ1w4n42Y</link>
<thumbnail>http://images.vozpopuli.com/2017/07/01/altavoz/play/Imagen-archivo-Camaron-Isla_1040606263_8375673_660x371.jpg</thumbnail>
</item>


<item>
<title>[COLOR green]Camaron de juerga  [/COLOR][COLOR yellow] con su familia completa[/COLOR]</title>
<link>plugin://plugin.video.youtube/?action=play_video&amp;videoid=JFrmeemg35Q</link>
<thumbnail>https://i.ytimg.com/vi/JFrmeemg35Q/hqdefault.jpg</thumbnail>
</item>

<item>
<title>[COLOR green]camaron en el rocio con chocolate,[/COLOR][COLOR yellow]rancapino,capullo,morao y otros [/COLOR]</title>
<link>plugin://plugin.video.youtube/?action=play_video&amp;videoid=FXZnYZfmRag</link>
<thumbnail>https://i.ytimg.com/vi/FXZnYZfmRag/hqdefault.jpg</thumbnail>
</item>

